{"id": "aced03e4-93ab-4b03-aa9d-f1a4ac68796d", "code": "\"\"\"\nHuman-designed MoE Scaling Law\nlog L(N,E) = a*log N + b*log \u00ca + c*log N * log \u00ca + d\nwhere 1/\u00ca = 1/(E-1+(1/E_start - 1/E_max)) + 1/E_max\n\"\"\"\nimport numpy as np\nimport pandas as pd\nimport os\nfrom scipy.optimize import minimize\n\ndef scaling_law_func(num_experts, total_parameter_count, params):\n    \"\"\"\n    Human-designed MoE scaling law function.\n    \n    log L(N,E) = a*log N + b*log \u00ca + c*log N * log \u00ca + d\n    where 1/\u00ca =  defined below\n    \n    Simplified version using 6 parameters: [a, b, c, d, E_start, E_max]\n    \"\"\"\n    a, b, c, d, E_start, E_max = params\n    \n    # Convert to numpy arrays and ensure positive values\n    E = np.asarray(num_experts, dtype=float) + 1e-8\n    N = np.asarray(total_parameter_count, dtype=float) + 1e-8\n    \n    # Enforce minimums on E_start and E_max\n    E_start = max(E_start, 1.1)\n    E_max = max(E_max, E_start + 1.0)\n    \n    # Compute \u00ca\n    denom = E - 1.0 + (1.0 / E_start - 1.0 / E_max)\n    denom = np.maximum(denom, 1e-8)\n    one_over_E_hat = 1.0 / denom + 1.0 / E_max\n    E_hat = 1.0 / np.maximum(one_over_E_hat, 1e-8)\n    \n    # Log terms\n    log_N = np.log(N)\n    log_E_hat = np.log(np.maximum(E_hat, 1e-8))\n    \n    # Scaling law in log-domain\n    log_loss = a * log_N + b * log_E_hat + c * log_N * log_E_hat + d\n    loss = np.exp(log_loss)\n    return loss\n\n# EVOLVE-BLOCK-START\ndef fit_scaling_law(num_experts, total_parameter_count, loss_values):\n    \"\"\"\n    Fit the human-designed MoE scaling law to data using\n    a two-step approach: linear initialization in log-domain\n    then robust non-linear least-squares with smooth transforms.\n    \"\"\"\n    # Convert inputs to numpy arrays\n    E_arr = np.asarray(num_experts, dtype=float)\n    N_arr = np.asarray(total_parameter_count, dtype=float)\n    L_arr = np.asarray(loss_values, dtype=float)\n    # Avoid zeros for log-domain\n    y_target = np.log(L_arr + 1e-12)\n\n    # Linear regression init on simplified log model: y = a log N + b log E + d\n    logN = np.log(N_arr + 1e-8)\n    logE = np.log(E_arr + 1e-8)\n    A = np.vstack([logN, logE, np.ones_like(logN)]).T\n    theta, *_ = np.linalg.lstsq(A, y_target, rcond=None)\n    a0, b0, d0 = theta\n    c0 = 0.0\n\n    # Initial E_start and E_max guesses via log-transform\n    E_start0 = 2.0\n    ru0 = np.log(E_start0 - 1.0)               # so E_start = 1 + exp(ru)\n    E_max0 = max(E_arr.max(), E_start0 + 1.0)\n    rv0 = np.log(max(E_max0 - E_start0, 1.0))  # so E_max = E_start + exp(rv)\n\n    init_raw = np.array([a0, b0, c0, d0, ru0, rv0], dtype=float)\n\n    # Helper to unpack raw parameters into physical ones\n    def unpack(raw):\n        a, b, c, d, ru, rv = raw\n        E_start = 1.0 + np.exp(ru)\n        E_max = E_start + np.exp(rv)\n        return a, b, c, d, E_start, E_max\n\n    # Residuals in log-domain\n    def residuals(raw):\n        a, b, c, d, E_start, E_max = unpack(raw)\n        params = np.array([a, b, c, d, E_start, E_max], dtype=float)\n        pred = scaling_law_func(E_arr, N_arr, params)\n        log_pred = np.log(pred + 1e-12)\n        return log_pred - y_target\n\n    # Robust non-linear least squares\n    from scipy.optimize import least_squares\n    result = least_squares(\n        residuals,\n        init_raw,\n        method='trf',\n        loss='soft_l1',\n        f_scale=1.0,\n        xtol=1e-12,\n        ftol=1e-12,\n        gtol=1e-12,\n        max_nfev=10000\n    )\n\n    # Fallback to L-BFGS-B on objective if LS fails\n    if not result.success:\n        def obj(raw):\n            r = residuals(raw)\n            return 0.5 * np.mean(r**2)\n        result = minimize(\n            obj,\n            init_raw,\n            method='L-BFGS-B',\n            options={'maxiter': 10000, 'ftol': 1e-12, 'gtol': 1e-8}\n        )\n\n    # Unpack final parameters\n    a_opt, b_opt, c_opt, d_opt, E_start_opt, E_max_opt = unpack(result.x)\n    return np.array([a_opt, b_opt, c_opt, d_opt, E_start_opt, E_max_opt], dtype=float)\n# EVOLVE-BLOCK-END\n\n# Set the number of parameters this function expects\nscaling_law_func.num_params = 6", "language": "python", "parent_id": "b56b4076-8b29-492c-b1c5-07be17618b71", "generation": 2, "timestamp": 1752941628.0607631, "iteration_found": 42, "metrics": {"mse": 0.0028693043801852644, "r2": 0.9656146154231481, "mae": 0.03950460644371338, "nmse": 0.034385384576851946, "combined_score": 0.9667576658665585}, "complexity": 0.0, "diversity": 0.0, "metadata": {"changes": "Full rewrite", "parent_metrics": {"mse": 0.0035318389820892778, "r2": 0.9576748836751799, "mae": 0.0451977075157671, "nmse": 0.04232511632482009, "combined_score": 0.9593935561352909}, "island": 1}, "artifacts_json": null, "artifact_dir": null, "prompts": {"full_rewrite_user": {"system": "You are an expert in scaling laws and machine learning optimization who specializes in improving parameter fitting algorithms for Mixture of Experts (MoE) scaling law functions. Your task is to evolve ONLY the `fit_scaling_law` optimization algorithm to better fit the given scaling law function to data.\n\n**CRITICAL CONSTRAINTS:**\n- The `scaling_law_func` function MUST remain completely unchanged\n- Only evolve code within # EVOLVE-BLOCK-START and # EVOLVE-BLOCK-END markers\n- The fit_scaling_law function signature must remain exactly the same\n- Focus on improving optimization algorithms, parameter initialization, bounds, constraints, and numerical stability\n\n**MOE SCALING LAW DETAILS:**\n- Scaling law function: log L(N,E) = a*log N + b*log \u00ca + c*log N * log \u00ca + d\n- Where: 1/\u00ca = 1/(E-1+(1/E_start - 1/E_max)) + 1/E_max\n- Parameters: 6 parameters [a, b, c, d, E_start, E_max]\n- Function signature: scaling_law_func(num_experts, total_parameter_count, params)\n- Fit function signature: fit_scaling_law(num_experts, total_parameter_count, loss_values)\n\n**DATA CHARACTERISTICS:**\n- Number of experts (E): Varying expert counts in MoE models\n- Total parameter count (N): Model size including all expert parameters\n- Loss values: Target losses to fit\n- The relationship models how loss scales with both model size and expert count\n\nWrite all improvements between # EVOLVE-BLOCK-START and # EVOLVE-BLOCK-END markers only.\n", "user": "# Current Program Information\n- Current performance metrics: - mse: 0.0035\n- r2: 0.9577\n- mae: 0.0452\n- nmse: 0.0423\n- combined_score: 0.9594\n- Areas identified for improvement: - Consider simplifying the code to improve readability and maintainability\n- Metrics showing improvement: mse, mae, nmse. Consider continuing with similar changes.\n- Metrics showing regression: r2, combined_score. Consider reverting or revising recent changes in these areas.\n\n\n\n# Program Evolution History\n## Previous Attempts\n\n### Attempt 3\n- Changes: Unknown changes\n- Performance: mse: 0.0029, r2: 0.9656, mae: 0.0395, nmse: 0.0344, combined_score: 0.9668\n- Outcome: Improvement in all metrics\n\n\n### Attempt 2\n- Changes: Unknown changes\n- Performance: mse: 0.0029, r2: 0.9658, mae: 0.0394, nmse: 0.0342, combined_score: 0.9669\n- Outcome: Improvement in all metrics\n\n\n### Attempt 1\n- Changes: Unknown changes\n- Performance: mse: 6.4357, r2: -76.1246, mae: 2.5200, nmse: 77.1246, combined_score: 0.0128\n- Outcome: Mixed results\n\n## Top Performing Programs\n\n### Program 1 (Score: 1.9937)\n```python\n\"\"\"\nHuman-designed MoE Scaling Law\nlog L(N,E) = a*log N + b*log \u00ca + c*log N * log \u00ca + d\nwhere 1/\u00ca = 1/(E-1+(1/E_start - 1/E_max)) + 1/E_max\n\"\"\"\nimport numpy as np\nimport pandas as pd\nimport os\nfrom scipy.optimize import minimize\n\n# ... (truncated for brevity)\n```\nKey features: Performs well on mse (6.4357), Performs well on r2 (-76.1246), Performs well on mae (2.5200), Performs well on nmse (77.1246), Performs well on combined_score (0.0128)\n\n\n### Program 2 (Score: 0.4018)\n```python\n\"\"\"\nHuman-designed MoE Scaling Law\nlog L(N,E) = a*log N + b*log \u00ca + c*log N * log \u00ca + d\nwhere 1/\u00ca = 1/(E-1+(1/E_start - 1/E_max)) + 1/E_max\n\"\"\"\nimport numpy as np\nimport pandas as pd\nimport os\nfrom scipy.optimize import minimize  # kept for backward compatibility\n# Note: we'll import least_squares inside the fit function\n# ... (truncated for brevity)\n```\nKey features: Performs well on mse (0.0029), Performs well on r2 (0.9658), Performs well on mae (0.0394), Performs well on nmse (0.0342), Performs well on combined_score (0.9669)\n\n\n### Program 3 (Score: 0.4018)\n```python\n\"\"\"\nHuman-designed MoE Scaling Law\nlog L(N,E) = a*log N + b*log \u00ca + c*log N * log \u00ca + d\nwhere 1/\u00ca = 1/(E-1+(1/E_start - 1/E_max)) + 1/E_max\n\"\"\"\nimport numpy as np\nimport pandas as pd\nimport os\nfrom scipy.optimize import minimize  # kept for compatibility, not used in fitting below\n\n# ... (truncated for brevity)\n```\nKey features: Performs well on mse (0.0029), Performs well on r2 (0.9656), Performs well on mae (0.0395), Performs well on nmse (0.0344), Performs well on combined_score (0.9668)\n\n\n\n\n## Diverse Programs\n\n### Program D1 (Score: 0.4018)\n```python\n\"\"\"\nHuman-designed MoE Scaling Law\nlog L(N,E) = a*log N + b*log \u00ca + c*log N * log \u00ca + d\nwhere 1/\u00ca = 1/(E-1+(1/E_start - 1/E_max)) + 1/E_max\n\"\"\"\n# ... (truncated)\n```\nKey features: Alternative approach to mse, Alternative approach to r2\n\n\n### Program D2 (Score: 0.4018)\n```python\n\"\"\"\nHuman-designed MoE Scaling Law\nlog L(N,E) = a*log N + b*log \u00ca + c*log N * log \u00ca + d\nwhere 1/\u00ca = 1/(E-1+(1/E_start - 1/E_max)) + 1/E_max\n\"\"\"\n# ... (truncated)\n```\nKey features: Alternative approach to mse, Alternative approach to r2\n\n## Inspiration Programs\n\nThese programs represent diverse approaches and creative solutions that may inspire new ideas:\n\n### Inspiration 1 (Score: 0.4018, Type: Experimental)\n```python\n\"\"\"\nHuman-designed MoE Scaling Law\nlog L(N,E) = a*log N + b*log \u00ca + c*log N * log \u00ca + d\nwhere 1/\u00ca = 1/(E-1+(1/E_start - 1/E_max)) + 1/E_max\n\"\"\"\nimport numpy as np\nimport pandas as pd\nimport os\n# ... (truncated for brevity)\n```\nUnique approach: Modification: Full rewrite, Alternative mse approach, Excellent r2 (0.966)\n\n\n### Inspiration 2 (Score: 1.9937, Type: High-Performer)\n```python\n\"\"\"\nHuman-designed MoE Scaling Law\nlog L(N,E) = a*log N + b*log \u00ca + c*log N * log \u00ca + d\nwhere 1/\u00ca = 1/(E-1+(1/E_start - 1/E_max)) + 1/E_max\n\"\"\"\nimport numpy as np\nimport pandas as pd\nimport os\n# ... (truncated for brevity)\n```\nUnique approach: Excellent mse (6.436), Alternative r2 approach, Excellent mae (2.520)\n\n\n### Inspiration 3 (Score: 0.4018, Type: Experimental)\n```python\n\"\"\"\nHuman-designed MoE Scaling Law\nlog L(N,E) = a*log N + b*log \u00ca + c*log N * log \u00ca + d\nwhere 1/\u00ca = 1/(E-1+(1/E_start - 1/E_max)) + 1/E_max\n\"\"\"\nimport numpy as np\nimport pandas as pd\nimport os\n# ... (truncated for brevity)\n```\nUnique approach: Modification: Full rewrite, Alternative mse approach, Excellent r2 (0.965)\n\n\n### Inspiration 4 (Score: 0.4018, Type: Experimental)\n```python\n\"\"\"\nHuman-designed MoE Scaling Law\nlog L(N,E) = a*log N + b*log \u00ca + c*log N * log \u00ca + d\nwhere 1/\u00ca = 1/(E-1+(1/E_start - 1/E_max)) + 1/E_max\n\"\"\"\nimport numpy as np\nimport pandas as pd\nimport os\n# ... (truncated for brevity)\n```\nUnique approach: Modification: Full rewrite, Alternative mse approach, Excellent r2 (0.966)\n\n\n### Inspiration 5 (Score: 0.3986, Type: Exploratory)\n```python\n\"\"\"\nHuman-designed MoE Scaling Law\nlog L(N,E) = a*log N + b*log \u00ca + c*log N * log \u00ca + d\nwhere 1/\u00ca = 1/(E-1+(1/E_start - 1/E_max)) + 1/E_max\n\"\"\"\nimport numpy as np\nimport pandas as pd\nimport os\n# ... (truncated for brevity)\n```\nUnique approach: Modification: Full rewrite, Alternative mse approach, Excellent r2 (0.907)\n\n\n\n# Current Program\n```python\n\"\"\"\nHuman-designed MoE Scaling Law\nlog L(N,E) = a*log N + b*log \u00ca + c*log N * log \u00ca + d\nwhere 1/\u00ca = 1/(E-1+(1/E_start - 1/E_max)) + 1/E_max\n\"\"\"\nimport numpy as np\nimport pandas as pd\nimport os\nfrom scipy.optimize import minimize\n\ndef scaling_law_func(num_experts, total_parameter_count, params):\n    \"\"\"\n    Human-designed MoE scaling law function.\n    \n    log L(N,E) = a*log N + b*log \u00ca + c*log N * log \u00ca + d\n    where 1/\u00ca = 1/(E-1+(1/E_start - 1/E_max)) + 1/E_max\n    \n    Simplified version using 6 parameters: [a, b, c, d, E_start, E_max]\n    \n    Args:\n        num_experts: Array of number of experts (E)\n        total_parameter_count: Array of total parameter counts (N)\n        params: Array of parameters [a, b, c, d, E_start, E_max] (6 parameters)\n        \n    Returns:\n        Predicted loss values\n    \"\"\"\n    a, b, c, d, E_start, E_max = params\n    \n    # Convert to numpy arrays and ensure positive values\n    E = np.asarray(num_experts, dtype=float) + 1e-8\n    N = np.asarray(total_parameter_count, dtype=float) + 1e-8\n    \n    # Enforce minimums on E_start and E_max\n    E_start = max(E_start, 1.1)\n    E_max = max(E_max, E_start + 1.0)\n    \n    # Compute \u00ca\n    denom = E - 1.0 + (1.0 / E_start - 1.0 / E_max)\n    denom = np.maximum(denom, 1e-8)\n    one_over_E_hat = 1.0 / denom + 1.0 / E_max\n    E_hat = 1.0 / np.maximum(one_over_E_hat, 1e-8)\n    \n    # Log terms\n    log_N = np.log(N)\n    log_E_hat = np.log(np.maximum(E_hat, 1e-8))\n    \n    # Scaling law\n    log_loss = a * log_N + b * log_E_hat + c * log_N * log_E_hat + d\n    loss = np.exp(log_loss)\n    return loss\n\n# EVOLVE-BLOCK-START\ndef fit_scaling_law(num_experts, total_parameter_count, loss_values):\n    \"\"\"\n    Fit the human-designed MoE scaling law to data using a robust log-domain\n    optimization and parameter transforms to enforce constraints.\n    \n    Args:\n        num_experts: Array of number of experts\n        total_parameter_count: Array of total parameter counts\n        loss_values: Array of corresponding loss values\n        \n    Returns:\n        Optimized parameters [a, b, c, d, E_start, E_max]\n    \"\"\"\n    # Convert inputs to numpy arrays\n    E_arr = np.asarray(num_experts, dtype=float)\n    N_arr = np.asarray(total_parameter_count, dtype=float)\n    L_arr = np.asarray(loss_values, dtype=float)\n    # Work in log-loss domain for stability\n    y_target = np.log(L_arr + 1e-12)\n\n    def objective(raw_params):\n        # raw_params = [a, b, c, d, ru, rv]\n        a, b, c, d, ru, rv = raw_params\n        # Enforce E_start > 1.0, E_max > E_start via absolute transforms\n        E_start = 1.0 + np.abs(ru)\n        E_max = E_start + np.abs(rv)\n        params = np.array([a, b, c, d, E_start, E_max], dtype=float)\n        # Predict and take log\n        pred = scaling_law_func(E_arr, N_arr, params)\n        log_pred = np.log(pred + 1e-12)\n        # Mean squared error in log-domain\n        return np.mean((log_pred - y_target)**2)\n\n    # Initial guess (raw): transforms yield E_start=2.0, E_max=100.0\n    init_raw = np.array([\n        -0.5,      # a\n        -0.5,      # b\n         0.1,      # c\n         0.0,      # d\n         1.0,      # ru => abs(1.0)+1 = 2.0\n         98.0      # rv => abs(98)+E_start = 100.0\n    ], dtype=float)\n\n    # First pass with L-BFGS-B\n    result = minimize(\n        objective,\n        init_raw,\n        method='L-BFGS-B',\n        options={'maxiter': 10000, 'ftol': 1e-12, 'gtol': 1e-8}\n    )\n\n    # Fallback to unconstrained if needed\n    if not result.success:\n        result = minimize(objective, init_raw, method='BFGS',\n                          options={'maxiter': 10000})\n\n    # Extract and transform back to physical parameters\n    a_opt, b_opt, c_opt, d_opt, ru_opt, rv_opt = result.x\n    E_start_opt = 1.0 + np.abs(ru_opt)\n    E_max_opt = E_start_opt + np.abs(rv_opt)\n    final_params = np.array([a_opt, b_opt, c_opt, d_opt, E_start_opt, E_max_opt])\n    return final_params\n# EVOLVE-BLOCK-END\n\n# Set the number of parameters this function expects\nscaling_law_func.num_params = 6\n```\n\n# Task\nRewrite the program to improve its performance on the specified metrics.\nProvide the complete new program code.\n\nIMPORTANT: Make sure your rewritten program maintains the same inputs and outputs\nas the original program, but with improved internal implementation.\n\n```python\n# Your rewritten program here\n```\n", "responses": ["```python\n\"\"\"\nHuman-designed MoE Scaling Law\nlog L(N,E) = a*log N + b*log \u00ca + c*log N * log \u00ca + d\nwhere 1/\u00ca = 1/(E-1+(1/E_start - 1/E_max)) + 1/E_max\n\"\"\"\nimport numpy as np\nimport pandas as pd\nimport os\nfrom scipy.optimize import minimize\n\ndef scaling_law_func(num_experts, total_parameter_count, params):\n    \"\"\"\n    Human-designed MoE scaling law function.\n    \n    log L(N,E) = a*log N + b*log \u00ca + c*log N * log \u00ca + d\n    where 1/\u00ca =  defined below\n    \n    Simplified version using 6 parameters: [a, b, c, d, E_start, E_max]\n    \"\"\"\n    a, b, c, d, E_start, E_max = params\n    \n    # Convert to numpy arrays and ensure positive values\n    E = np.asarray(num_experts, dtype=float) + 1e-8\n    N = np.asarray(total_parameter_count, dtype=float) + 1e-8\n    \n    # Enforce minimums on E_start and E_max\n    E_start = max(E_start, 1.1)\n    E_max = max(E_max, E_start + 1.0)\n    \n    # Compute \u00ca\n    denom = E - 1.0 + (1.0 / E_start - 1.0 / E_max)\n    denom = np.maximum(denom, 1e-8)\n    one_over_E_hat = 1.0 / denom + 1.0 / E_max\n    E_hat = 1.0 / np.maximum(one_over_E_hat, 1e-8)\n    \n    # Log terms\n    log_N = np.log(N)\n    log_E_hat = np.log(np.maximum(E_hat, 1e-8))\n    \n    # Scaling law in log-domain\n    log_loss = a * log_N + b * log_E_hat + c * log_N * log_E_hat + d\n    loss = np.exp(log_loss)\n    return loss\n\n# EVOLVE-BLOCK-START\ndef fit_scaling_law(num_experts, total_parameter_count, loss_values):\n    \"\"\"\n    Fit the human-designed MoE scaling law to data using\n    a two-step approach: linear initialization in log-domain\n    then robust non-linear least-squares with smooth transforms.\n    \"\"\"\n    # Convert inputs to numpy arrays\n    E_arr = np.asarray(num_experts, dtype=float)\n    N_arr = np.asarray(total_parameter_count, dtype=float)\n    L_arr = np.asarray(loss_values, dtype=float)\n    # Avoid zeros for log-domain\n    y_target = np.log(L_arr + 1e-12)\n\n    # Linear regression init on simplified log model: y = a log N + b log E + d\n    logN = np.log(N_arr + 1e-8)\n    logE = np.log(E_arr + 1e-8)\n    A = np.vstack([logN, logE, np.ones_like(logN)]).T\n    theta, *_ = np.linalg.lstsq(A, y_target, rcond=None)\n    a0, b0, d0 = theta\n    c0 = 0.0\n\n    # Initial E_start and E_max guesses via log-transform\n    E_start0 = 2.0\n    ru0 = np.log(E_start0 - 1.0)               # so E_start = 1 + exp(ru)\n    E_max0 = max(E_arr.max(), E_start0 + 1.0)\n    rv0 = np.log(max(E_max0 - E_start0, 1.0))  # so E_max = E_start + exp(rv)\n\n    init_raw = np.array([a0, b0, c0, d0, ru0, rv0], dtype=float)\n\n    # Helper to unpack raw parameters into physical ones\n    def unpack(raw):\n        a, b, c, d, ru, rv = raw\n        E_start = 1.0 + np.exp(ru)\n        E_max = E_start + np.exp(rv)\n        return a, b, c, d, E_start, E_max\n\n    # Residuals in log-domain\n    def residuals(raw):\n        a, b, c, d, E_start, E_max = unpack(raw)\n        params = np.array([a, b, c, d, E_start, E_max], dtype=float)\n        pred = scaling_law_func(E_arr, N_arr, params)\n        log_pred = np.log(pred + 1e-12)\n        return log_pred - y_target\n\n    # Robust non-linear least squares\n    from scipy.optimize import least_squares\n    result = least_squares(\n        residuals,\n        init_raw,\n        method='trf',\n        loss='soft_l1',\n        f_scale=1.0,\n        xtol=1e-12,\n        ftol=1e-12,\n        gtol=1e-12,\n        max_nfev=10000\n    )\n\n    # Fallback to L-BFGS-B on objective if LS fails\n    if not result.success:\n        def obj(raw):\n            r = residuals(raw)\n            return 0.5 * np.mean(r**2)\n        result = minimize(\n            obj,\n            init_raw,\n            method='L-BFGS-B',\n            options={'maxiter': 10000, 'ftol': 1e-12, 'gtol': 1e-8}\n        )\n\n    # Unpack final parameters\n    a_opt, b_opt, c_opt, d_opt, E_start_opt, E_max_opt = unpack(result.x)\n    return np.array([a_opt, b_opt, c_opt, d_opt, E_start_opt, E_max_opt], dtype=float)\n# EVOLVE-BLOCK-END\n\n# Set the number of parameters this function expects\nscaling_law_func.num_params = 6\n```"]}}}